Workbook

Sheet Read me
A1: Heroes Arena 3-year model, v0.2 DRAFT (30 Oct 2026)
A3: Internal. Not for schools. A desk model for discussion, not a forecast, quote or advice.
A5: How to use it
A6: 1. Summary: the 3-year picture against today in rented halls, with a chart.
A7: 2. Assumptions: every input, with its source. Change the case in cell C3 (1 Downside, 2 Cautious, 3 Target).
A8: 3. Monthly: 36 months from opening, built only from the Assumptions sheet.
A9: 4. Build and funding: the build cost floor and how it might be paid for.
A10: 5. Funding routes: which body applies for what, and how the CIC and the Ltd work together.
A12: Colours
A13: Blue text = an input you can change. Black = a formula. Yellow = the case selector.
A15: Labels (as in the KB)
A16: Actual = invoices or live systems. Indicative = a supplier's informal figure. List price = published price. Desk estimate = our own calculation. Jamie assumption = a figure Jamie set.

Sheet Summary
A1: Heroes Arena: 3-year summary
A2: =CONCATENATE("Case shown: ",Assumptions!$D$3,". Internal draft for discussion. Every input is labelled on the Assumptions sheet.")
B4: Today, rented halls (per year) | C4: Arena Year 1 | D4: Arena Year 2 | E4: Arena Year 3
A5: Members at year end | B5: =Assumptions!$F$100 | C5: =Monthly!N9 | D5: =Monthly!Z9 | E5: =Monthly!AL9
A6: Class sessions a week at year end | B6: =Assumptions!$F$102 | C6: =Monthly!N13 | D6: =Monthly!Z13 | E6: =Monthly!AL13
A7: Court hours used, share of usable hours | C7: =Monthly!N60 | D7: =Monthly!Z60 | E7: =Monthly!AL60
A9: Income
A10: Memberships, multi-session plans and joining fees | B10: =Assumptions!$F$100*Assumptions!$F$12*12*(1-Assumptions!$F$21) | C10: =SUMIF(Monthly!$C$5:$AL$5,1,Monthly!$C$16:$AL$16)+SUMIF(Monthly!$C$5:$AL$5,1,Monthly!$C$17:$AL$17)+SUMIF(Monthly!$C$5:$AL$5,1,Monthly!$C$18:$AL$18)+SUMIF(Monthly!$C$5:$AL$5,1,Monthly!$C$19:$AL$19) | D10: =SUMIF(Monthly!$C$5:$AL$5,2,Monthly!$C$16:$AL$16)+SUMIF(Monthly!$C$5:$AL$5,2,Monthly!$C$17:$AL$17)+SUMIF(Monthly!$C$5:$AL$5,2,Monthly!$C$18:$AL$18)+SUMIF(Monthly!$C$5:$AL$5,2,Monthly!$C$19:$AL$19) | E10: =SUMIF(Monthly!$C$5:$AL$5,3,Monthly!$C$16:$AL$16)+SUMIF(Monthly!$C$5:$AL$5,3,Monthly!$C$17:$AL$17)+SUMIF(Monthly!$C$5:$AL$5,3,Monthly!$C$18:$AL$18)+SUMIF(Monthly!$C$5:$AL$5,3,Monthly!$C$19:$AL$19)
A11: Birthday parties and 3x3 tournaments | B11: 0 | C11: =SUMIF(Monthly!$C$5:$AL$5,1,Monthly!$C$20:$AL$20)+SUMIF(Monthly!$C$5:$AL$5,1,Monthly!$C$21:$AL$21) | D11: =SUMIF(Monthly!$C$5:$AL$5,2,Monthly!$C$20:$AL$20)+SUMIF(Monthly!$C$5:$AL$5,2,Monthly!$C$21:$AL$21) | E11: =SUMIF(Monthly!$C$5:$AL$5,3,Monthly!$C$20:$AL$20)+SUMIF(Monthly!$C$5:$AL$5,3,Monthly!$C$21:$AL$21)
A12: Holiday camps and funded places | B12: 0 | C12: =SUMIF(Monthly!$C$5:$AL$5,1,Monthly!$C$22:$AL$22)+SUMIF(Monthly!$C$5:$AL$5,1,Monthly!$C$23:$AL$23) | D12: =SUMIF(Monthly!$C$5:$AL$5,2,Monthly!$C$22:$AL$22)+SUMIF(Monthly!$C$5:$AL$5,2,Monthly!$C$23:$AL$23) | E12: =SUMIF(Monthly!$C$5:$AL$5,3,Monthly!$C$22:$AL$22)+SUMIF(Monthly!$C$5:$AL$5,3,Monthly!$C$23:$AL$23)
A13: Breakfast All Stars and leagues | B13: 0 | C13: =SUMIF(Monthly!$C$5:$AL$5,1,Monthly!$C$24:$AL$24)+SUMIF(Monthly!$C$5:$AL$5,1,Monthly!$C$25:$AL$25) | D13: =SUMIF(Monthly!$C$5:$AL$5,2,Monthly!$C$24:$AL$24)+SUMIF(Monthly!$C$5:$AL$5,2,Monthly!$C$25:$AL$25) | E13: =SUMIF(Monthly!$C$5:$AL$5,3,Monthly!$C$24:$AL$24)+SUMIF(Monthly!$C$5:$AL$5,3,Monthly!$C$25:$AL$25)
A14: School PE support, hire and grants | B14: 0 | C14: =SUMIF(Monthly!$C$5:$AL$5,1,Monthly!$C$26:$AL$26)+SUMIF(Monthly!$C$5:$AL$5,1,Monthly!$C$27:$AL$27)+SUMIF(Monthly!$C$5:$AL$5,1,Monthly!$C$28:$AL$28) | D14: =SUMIF(Monthly!$C$5:$AL$5,2,Monthly!$C$26:$AL$26)+SUMIF(Monthly!$C$5:$AL$5,2,Monthly!$C$27:$AL$27)+SUMIF(Monthly!$C$5:$AL$5,2,Monthly!$C$28:$AL$28) | E14: =SUMIF(Monthly!$C$5:$AL$5,3,Monthly!$C$26:$AL$26)+SUMIF(Monthly!$C$5:$AL$5,3,Monthly!$C$27:$AL$27)+SUMIF(Monthly!$C$5:$AL$5,3,Monthly!$C$28:$AL$28)
A15: Total income | B15: =SUM(B10:B14) | C15: =SUM(C10:C14) | D15: =SUM(D10:D14) | E15: =SUM(E10:E14)
A17: Costs
A18: Coaching and session costs | B18: =Assumptions!$F$102*Assumptions!$F$20*Assumptions!$F$28+B10/(1-Assumptions!$F$21)*Assumptions!$F$22 | C18: =SUMIF(Monthly!$C$5:$AL$5,1,Monthly!$C$41:$AL$41) | D18: =SUMIF(Monthly!$C$5:$AL$5,2,Monthly!$C$41:$AL$41) | E18: =SUMIF(Monthly!$C$5:$AL$5,3,Monthly!$C$41:$AL$41)
A19: Hall rent | B19: =Assumptions!$F$101*12 | C19: =0 | D19: =0 | E19: =0
A20: Arena finance | B20: 0 | C20: =SUMIF(Monthly!$C$5:$AL$5,1,Monthly!$C$46:$AL$46) | D20: =SUMIF(Monthly!$C$5:$AL$5,2,Monthly!$C$46:$AL$46) | E20: =SUMIF(Monthly!$C$5:$AL$5,3,Monthly!$C$46:$AL$46)
A21: Arena running and heating | B21: 0 | C21: =SUMIF(Monthly!$C$5:$AL$5,1,Monthly!$C$47:$AL$47)+SUMIF(Monthly!$C$5:$AL$5,1,Monthly!$C$48:$AL$48)+SUMIF(Monthly!$C$5:$AL$5,1,Monthly!$C$49:$AL$49) | D21: =SUMIF(Monthly!$C$5:$AL$5,2,Monthly!$C$47:$AL$47)+SUMIF(Monthly!$C$5:$AL$5,2,Monthly!$C$48:$AL$48)+SUMIF(Monthly!$C$5:$AL$5,2,Monthly!$C$49:$AL$49) | E21: =SUMIF(Monthly!$C$5:$AL$5,3,Monthly!$C$47:$AL$47)+SUMIF(Monthly!$C$5:$AL$5,3,Monthly!$C$48:$AL$48)+SUMIF(Monthly!$C$5:$AL$5,3,Monthly!$C$49:$AL$49)
A22: Marketing, admin and kit | B22: 0 | C22: =SUMIF(Monthly!$C$5:$AL$5,1,Monthly!$C$50:$AL$50)+SUMIF(Monthly!$C$5:$AL$5,1,Monthly!$C$51:$AL$51)+SUMIF(Monthly!$C$5:$AL$5,1,Monthly!$C$52:$AL$52) | D22: =SUMIF(Monthly!$C$5:$AL$5,2,Monthly!$C$50:$AL$50)+SUMIF(Monthly!$C$5:$AL$5,2,Monthly!$C$51:$AL$51)+SUMIF(Monthly!$C$5:$AL$5,2,Monthly!$C$52:$AL$52) | E22: =SUMIF(Monthly!$C$5:$AL$5,3,Monthly!$C$50:$AL$50)+SUMIF(Monthly!$C$5:$AL$5,3,Monthly!$C$51:$AL$51)+SUMIF(Monthly!$C$5:$AL$5,3,Monthly!$C$52:$AL$52)
A23: Total costs | B23: =SUM(B18:B22) | C23: =SUM(C18:C22) | D23: =SUM(D18:D22) | E23: =SUM(E18:E22)
A25: SITE PROFIT (before central overheads) | B25: =B15-B23 | C25: =C15-C23 | D25: =D15-D23 | E25: =E15-E23
A26: Profit margin | B26: =IF(B15=0,0,B25/B15) | C26: =IF(C15=0,0,C25/C15) | D26: =IF(D15=0,0,D25/D15) | E26: =IF(E15=0,0,E25/E15)
A27: Extra profit vs rented halls | C27: =C25-$B$25 | D27: =D25-$B$25 | E27: =E25-$B$25
A28: Income per member a year | B28: =IF(B5=0,0,B15/B5) | C28: =IF(C5=0,0,C15/C5) | D28: =IF(D5=0,0,D15/D5) | E28: =IF(E5=0,0,E15/E5)
A30: Notes
A31: "Today" is Aylesbury and Wendover in rented halls for a year at today's members, with no growth: halls cap the timetable.
A32: Site profit is before central overheads (management, head office, owner pay). The Arena column also carries its own marketing, admin and kit, so the comparison is cautious.
A33: Capacity: the Arena has about 45 usable court hours a week against 3 hours in halls today. Above about 90% the timetable is full.
A34: On rent saved alone the Arena does not pay its way (Project Overview v0.2). The extra profit comes from growth: more members, 2nd sessions, parties, camps, breakfast and leagues.
A35: Not included: business rates, structure insurance above the running allowance, professional fees and any build costs not covered by finance (see Build and funding).
A36: Figures are a desk model for discussion, not a forecast or advice. VAT, CIC and finance terms to confirm with the accountant.

Sheet Assumptions
A1: Heroes Arena: assumptions
A2: Blue = input you can change. Pick the case in C3; every other sheet follows. Labels say where each figure comes from.
A3: Case shown (1 = Downside, 2 = Cautious, 3 = Target) | C3: 3 | D3: =CHOOSE($C$3,"Downside","Cautious","Target")
A5: Assumption | B5: Unit | C5: Downside | D5: Cautious | E5: Target | F5: Live (case shown) | G5: Source / label
A6: Opening and members
A7: Arena opens | B7: date | C7: 46631 | D7: 46631 | E7: 46631 | F7: =CHOOSE($C$3,C7,D7,E7) | G7: Desk assumption: September 2027 (planning note v1.0: summer 2027 is the realistic fast date)
A8: Members on opening (moving in) | B8: members | C8: 78 | D8: 100 | E8: 100 | F8: =CHOOSE($C$3,C8,D8,E8) | G8: Jamie assumption: 100+ (Aylesbury 31 + Wendover 67 = 98, actual TeamUp 26 Oct 2026). Downside uses the KB retention case (~78 move)
A9: Members, end of Year 1 | B9: members | C9: 110 | D9: 150 | E9: 220 | F9: =CHOOSE($C$3,C9,D9,E9) | G9: Jamie assumption (target); cautious and downside are desk estimates
A10: Members, end of Year 2 | B10: members | C10: 140 | D10: 200 | E10: 320 | F10: =CHOOSE($C$3,C10,D10,E10) | G10: Jamie assumption (target); cautious and downside are desk estimates
A11: Members, end of Year 3 | B11: members | C11: 170 | D11: 250 | E11: 400 | F11: =CHOOSE($C$3,C11,D11,E11) | G11: Target 400: Jamie, 29 Oct 2026. Cautious 250: KB growth case (HHOS 2.0 / Project Overview v0.2)
A12: Membership fee, realised per member | B12: £/month | C12: 35 | D12: 35 | E12: 35 | F12: =CHOOSE($C$3,C12,D12,E12) | G12: Actual: £34.73–£35 realised fee (Project Overview v0.2, Finance)
A13: Members adding a 2nd weekly session | B13: % of members | C13: 0.15 | D13: 0.2 | E13: 0.25 | F13: =CHOOSE($C$3,C13,D13,E13) | G13: Desk estimate (HHOS 2.0 suggests about a third on multi-session plans)
A14: 2nd weekly session price | B14: £/month | C14: 25 | D14: 25 | E14: 25 | F14: =CHOOSE($C$3,C14,D14,E14) | G14: Jamie, 29 Oct 2026
A15: Members on a 3-a-week plan | B15: % of members | C15: 0.03 | D15: 0.05 | E15: 0.08 | F15: =CHOOSE($C$3,C15,D15,E15) | G15: Desk estimate
A16: 3-a-week plan price, on top of the membership | B16: £/month | C16: 40 | D16: 40 | E16: 40 | F16: =CHOOSE($C$3,C16,D16,E16) | G16: Jamie, 29 Oct 2026
A17: Joining fee per new member | B17: £ | C17: 45 | D17: 45 | E17: 45 | F17: =CHOOSE($C$3,C17,D17,E17) | G17: Jamie, 29 Oct 2026. Families moving in from today's classes don't pay it
A18: Members leaving each month (replaced by new joiners) | B18: % a month | C18: 0.025 | D18: 0.025 | E18: 0.025 | F18: =CHOOSE($C$3,C18,D18,E18) | G18: Desk estimate; to replace with TeamUp actuals
... A22: Card and payment fees | B22: % of sales | C22: 0.02 | D22: 0.02 | E22: 0.02 | F22: =CHOOSE($C$3,C22,D22,E22) | G22: Desk estimate (Stripe)
A23: Coaching (one head coach + one assistant per session)
A24: Head coach pay | B24: £/hour | C24: 25 | D24: 25 | E24: 25 | F24: =CHOOSE($C$3,C24,D24,E24) | G24: Jamie, 29 Oct 2026
A25: Assistant coach pay | B25: £/hour | C25: 15 | D25: 15 | E25: 15 | F25: =CHOOSE($C$3,C25,D25,E25) | G25: Jamie, 29 Oct 2026
A26: Paid hours per 1-hour session | B26: hours | C26: 1.25 | D26: 1.25 | E26: 1.25 | F26: =CHOOSE($C$3,C26,D26,E26) | G26: Desk estimate: includes set-up and pack-down
A27: Employer on-costs (holiday pay, NI) | B27: % of pay | C27: 0.1 | D27: 0.1 | E27: 0.1 | F27: =CHOOSE($C$3,C27,D27,E27) | G27: Desk estimate; confirm with Finance
A28: Cost of one coached session | B28: £/session | C28: =(C24+C25)*C26*(1+C27) | D28: =(D24+D25)*D26*(1+D27) | E28: =(E24+E25)*E26*(1+E27) | F28: =(F24+F25)*F26*(1+F27) | G28: Formula
A29: Court hours we can use a week (outside the school day) | B29: hours | C29: 45 | D29: 45 | E29: 45 | F29: =CHOOSE($C$3,C29,D29,E29) | G29: Desk estimate: weekdays 3:30–8:30pm (25) + weekends 9am–7pm (20). Today: 3 hours a week in halls
A30: Birthday parties
A31: Party price | B31: £/party | C31: 225 | D31: 225 | E31: 225 | F31: =CHOOSE($C$3,C31,D31,E31) | G31: Jamie, 29 Oct 2026 (about 90 minutes, up to 20 children)
A32: Parties a week, Year 1 | B32: parties | C32: 0.5 | D32: 1 | E32: 1.5 | F32: =CHOOSE($C$3,C32,D32,E32) | G32: Desk estimate
A33: Parties a week, Year 2 | B33: parties | C33: 1 | D33: 1.5 | E33: 2.5 | F33: =CHOOSE($C$3,C33,D33,E33) | G33: Desk estimate
A34: Parties a week, Year 3 | B34: parties | C34: 1 | D34: 2 | E34: 3.5 | F34: =CHOOSE($C$3,C34,D34,E34) | G34: Desk estimate
A35: Staff hours per party (both coaches) | B35: hours | C35: 2 | D35: 2 | E35: 2 | F35: =CHOOSE($C$3,C35,D35,E35) | G35: Desk estimate
A36: Party extras (medals, kit, cleaning) | B36: £/party | C36: 25 | D36: 25 | E36: 25 | F36: =CHOOSE($C$3,C36,D36,E36) | G36: Desk estimate
A37: Court time per party | B37: hours | C37: 1.5 | D37: 1.5 | E37: 1.5 | F37: =CHOOSE($C$3,C37,D37,E37) | G37: Desk estimate
A38: 3x3 tournaments (one-day events, like Gameday)
A39: Tournaments a year, Year 1 | B39: events | C39: 2 | D39: 3 | E39: 4 | F39: =CHOOSE($C$3,C39,D39,E39) | G39: Desk estimate
A40: Tournaments a year, Year 2 | B40: events | C40: 3 | D40: 5 | E40: 6 | F40: =CHOOSE($C$3,C40,D40,E40) | G40: Desk estimate
A41: Tournaments a year, Year 3 | B41: events | C41: 4 | D41: 6 | E41: 8 | F41: =CHOOSE($C$3,C41,D41,E41) | G41: Desk estimate
A42: Players per tournament | B42: players | C42: 24 | D42: 32 | E42: 40 | F42: =CHOOSE($C$3,C42,D42,E42) | G42: Desk estimate (Gameday: 3 on court + 1 sub per team)
A43: Entry fee per player | B43: £ | C43: 30 | D43: 30 | E43: 30 | F43: =CHOOSE($C$3,C43,D43,E43) | G43: Actual: 3x3 Gameday £30 per player (website, Oct 2026)
A44: Coach hours per tournament (all staff) | B44: hours | C44: 12 | D44: 12 | E44: 12 | F44: =CHOOSE($C$3,C44,D44,E44) | G44: Desk estimate: 2 head + 2 assistant coaches for 3 hours
A45: Medals and extras per player | B45: £ | C45: 4 | D45: 4 | E45: 4 | F45: =CHOOSE($C$3,C45,D45,E45) | G45: Desk estimate
A46: Holiday camps
A47: Camp price | B47: £/child/day | C47: 35 | D47: 35 | E47: 35 | F47: =CHOOSE($C$3,C47,D47,E47) | G47: Jamie, 29 Oct 2026 (9am to 3pm)
A48: Share of holiday weeks we run, Year 1 | B48: % of 13 weeks | C48: 0.4 | D48: 0.5 | E48: 0.6 | F48: =CHOOSE($C$3,C48,D48,E48) | G48: Desk estimate
A49: Share of holiday weeks we run, Year 2 | B49: % of 13 weeks | C49: 0.6 | D49: 0.75 | E49: 0.9 | F49: =CHOOSE($C$3,C49,D49,E49) | G49: Desk estimate
A50: Share of holiday weeks we run, Year 3 | B50: % of 13 weeks | C50: 0.75 | D50: 1 | E50: 1 | F50: =CHOOSE($C$3,C50,D50,E50) | G50: Desk estimate
A51: Paying campers a day, Year 1 | B51: children | C51: 12 | D51: 16 | E51: 20 | F51: =CHOOSE($C$3,C51,D51,E51) | G51: Desk estimate
A52: Paying campers a day, Year 2 | B52: children | C52: 16 | D52: 20 | E52: 28 | F52: =CHOOSE($C$3,C52,D52,E52) | G52: Desk estimate
A53: Paying campers a day, Year 3 | B53: children | C53: 18 | D53: 24 | E53: 36 | F53: =CHOOSE($C$3,C53,D53,E53) | G53: Desk estimate
A54: Children per coach at camp | B54: children | C54: 12 | D54: 12 | E54: 12 | F54: =CHOOSE($C$3,C54,D54,E54) | G54: Desk estimate
A55: Staff hours per camp day | B55: hours | C55: 7 | D55: 7 | E55: 7 | F55: =CHOOSE($C$3,C55,D55,E55) | G55: Desk estimate (9am to 3pm plus set-up)
A56: Average coach rate at camp | B56: £/hour | C56: =(C24+C25)/2*(1+C27) | D56: =(D24+D25)/2*(1+D27) | E56: =(E24+E25)/2*(1+E27) | F56: =(F24+F25)/2*(1+F27) | G56: Formula
A57: Funded holiday places (Holiday Activities and Food programme)
A58: Funded places a day, Year 1 | B58: children | C58: 0 | D58: 10 | E58: 15 | F58: =CHOOSE($C$3,C58,D58,E58) | G58: Desk estimate; needs approval as a Bucks HAF provider
A59: Funded places a day, Year 2 | B59: children | C59: 10 | D59: 15 | E59: 20 | F59: =CHOOSE($C$3,C59,D59,E59) | G59: Desk estimate
A60: Funded places a day, Year 3 | B60: children | C60: 10 | D60: 20 | E60: 25 | F60: =CHOOSE($C$3,C60,D60,E60) | G60: Desk estimate
A61: HAF payment per place per day | B61: £ | C61: 25 | D61: 25 | E61: 25 | F61: =CHOOSE($C$3,C61,D61,E61) | G61: Desk estimate: to verify with Buckinghamshire Council HAF
A62: HAF days per HAF week | B62: days | C62: 4 | D62: 4 | E62: 4 | F62: =CHOOSE($C$3,C62,D62,E62) | G62: Desk estimate (HAF runs 4 days a week)
A63: Food and extra cost per HAF place per day | B63: £ | C63: 8 | D63: 8 | E63: 8 | F63: =CHOOSE($C$3,C63,D63,E63) | G63: Desk estimate
A64: Breakfast All Stars (before school)
A65: Price per morning | B65: £/child | C65: 7 | D65: 7 | E65: 7 | F65: =CHOOSE($C$3,C65,D65,E65) | G65: Desk estimate
A66: Mornings a week | B66: mornings | C66: 5 | D66: 5 | E66: 5 | F66: =CHOOSE($C$3,C66,D66,E66) | G66: Example week in the schools deck
A67: Children per morning, Year 1 | B67: children | C67: 6 | D67: 8 | E67: 10 | F67: =CHOOSE($C$3,C67,D67,E67) | G67: Desk estimate
A68: Children per morning, Year 2 | B68: children | C68: 8 | D68: 12 | E68: 15 | F68: =CHOOSE($C$3,C68,D68,E68) | G68: Desk estimate
A69: Children per morning, Year 3 | B69: children | C69: 10 | D69: 14 | E69: 20 | F69: =CHOOSE($C$3,C69,D69,E69) | G69: Desk estimate
A70: Head coach hours per morning | B70: hours | C70: 1.25 | D70: 1.25 | E70: 1.25 | F70: =CHOOSE($C$3,C70,D70,E70) | G70: Desk estimate (one coach)
A71: 3x3 leagues
A72: League fee per player per term | B72: £ | C72: 60 | D72: 60 | E72: 60 | F72: =CHOOSE($C$3,C72,D72,E72) | G72: Desk estimate
A73: League terms a year | B73: terms | C73: 3 | D73: 3 | E73: 3 | F73: =CHOOSE($C$3,C73,D73,E73) | G73: Desk estimate
A74: League players, Year 1 | B74: players | C74: 0 | D74: 24 | E74: 32 | F74: =CHOOSE($C$3,C74,D74,E74) | G74: Desk estimate
A75: League players, Year 2 | B75: players | C75: 24 | D75: 40 | E75: 60 | F75: =CHOOSE($C$3,C75,D75,E75) | G75: Desk estimate
A76: League players, Year 3 | B76: players | C76: 32 | D76: 48 | E76: 80 | F76: =CHOOSE($C$3,C76,D76,E76) | G76: Desk estimate
A77: League sessions a week | B77: sessions | C77: 2 | D77: 2 | E77: 2 | F77: =CHOOSE($C$3,C77,D77,E77) | G77: Desk estimate
A78: Other income
A79: School PE support and CPD, Year 1 | B79: £/year | C79: 1500 | D79: 3000 | E79: 4000 | F79: =CHOOSE($C$3,C79,D79,E79) | G79: Desk estimate; paid by the school from its PE and Sport Premium (revenue only)
A80: School PE support and CPD, Year 2 | B80: £/year | C80: 2500 | D80: 4000 | E80: 6000 | F80: =CHOOSE($C$3,C80,D80,E80) | G80: Desk estimate
A81: School PE support and CPD, Year 3 | B81: £/year | C81: 3000 | D81: 5000 | E81: 8000 | F81: =CHOOSE($C$3,C81,D81,E81) | G81: Desk estimate
A82: Hire of unused hours, Year 1 | B82: £/year | C82: 0 | D82: 0 | E82: 1000 | F82: =CHOOSE($C$3,C82,D82,E82) | G82: Desk estimate; school agreement and VAT to check
A83: Hire of unused hours, Year 2 | B83: £/year | C83: 0 | D83: 1500 | E83: 3000 | F83: =CHOOSE($C$3,C83,D83,E83) | G83: Desk estimate
A84: Hire of unused hours, Year 3 | B84: £/year | C84: 1000 | D84: 3000 | E84: 5000 | F84: =CHOOSE($C$3,C84,D84,E84) | G84: Desk estimate
A85: Community sessions (free, SEND, wheelchair, girls-only, over-40s)
A86: Community sessions a week | B86: sessions | C86: 2 | D86: 3 | E86: 4 | F86: =CHOOSE($C$3,C86,D86,E86) | G86: Desk estimate; timetable owned by the Coaching Director
A87: Share of their coaching cost paid by grants, Year 1 | B87: % of cost | C87: 0 | D87: 0 | E87: 0 | F87: =CHOOSE($C$3,C87,D87,E87) | G87: Jamie, 29 Oct 2026: Arena #1 runs through the Ltd; most community grants need a not-for-profit, so none in Year 1
A88: Share paid by grants, Year 2 | B88: % of cost | C88: 0.25 | D88: 0.5 | E88: 0.75 | F88: =CHOOSE($C$3,C88,D88,E88) | G88: Desk estimate: once a CIC is set up after Arena #1 is proven
A89: Share paid by grants, Year 3 | B89: % of cost | C89: 0.5 | D89: 0.75 | E89: 1 | F89: =CHOOSE($C$3,C89,D89,E89) | G89: Desk estimate
A90: Arena running costs
A91: Supplier finance (Zappshelter package) | B91: £/month | C91: 2000 | D91: 2000 | E91: 2000 | F91: =CHOOSE($C$3,C91,D91,E91) | G91: Indicative: Zappshelter, Peter Laird, 29 Oct 2026: about £2,000 + VAT a month over 5 years (about £3,000 over 3) for the £87,343 + VAT package. Containers not included. VAT treatment to confirm
A92: Finance term | B92: months | C92: 60 | D92: 60 | E92: 60 | F92: =CHOOSE($C$3,C92,D92,E92) | G92: Indicative, as above
A93: Running: insurance, power, maintenance, fabric fund | B93: £/month | C93: 1000 | D93: 1000 | E93: 750 | F93: =CHOOSE($C$3,C93,D93,E93) | G93: Desk estimate: HHOS 2.0 £6k–£12k a year
A94: Heating, per winter (Nov to Mar) | B94: £/winter | C94: 9500 | D94: 7550 | E94: 7550 | F94: =CHOOSE($C$3,C94,D94,E94) | G94: Desk estimate: £5.6k–£9.5k per winter (options paper v1.0); to re-estimate
A95: Rent to the school | B95: £/month | C95: 0 | D95: 0 | E95: 0 | F95: =CHOOSE($C$3,C95,D95,E95) | G95: Jamie, 29 Oct 2026: zero rent under the school agreement
A96: Marketing | B96: £/month | C96: 300 | D96: 300 | E96: 400 | F96: =CHOOSE($C$3,C96,D96,E96) | G96: Desk estimate
A97: Admin and systems | B97: £/month | C97: 250 | D97: 250 | E97: 250 | F97: =CHOOSE($C$3,C97,D97,E97) | G97: Desk estimate
A98: Kit replacement | B98: £/year | C98: 1500 | D98: 1000 | E98: 1000 | F98: =CHOOSE($C$3,C98,D98,E98) | G98: Desk estimate
A99: Today, in rented halls (for comparison)
A100: Members today (Aylesbury + Wendover) | B100: members | C100: 98 | D100: 98 | E100: 98 | F100: =CHOOSE($C$3,C100,D100,E100) | G100: Actual: TeamUp paid members, 26 Oct 2026
A101: Hall rent today | B101: £/month | C101: 607.85 | D101: 607.85 | E101: 607.85 | F101: =CHOOSE($C$3,C101,D101,E101) | G101: Actual: invoices and Finance model (Project Overview v0.2)
A102: Classes a week today | B102: classes | C102: 5 | D102: 5 | E102: 5 | F102: =CHOOSE($C$3,C102,D102,E102) | G102: Actual: TeamUp, 26 Oct 2026
A104: Holiday and winter calendar
A105: Month | B105: Month no. | C105: Camp weeks | D105: HAF weeks | E105: Heating month (1 = yes)
...

Sheet Monthly
A1: Heroes Arena: month by month, 36 months
A2: =CONCATENATE("Case shown: ",Assumptions!$D$3,". All £ after Flat Rate VAT. Change inputs on the Assumptions sheet only.")
B3: Month | C3: 1 | D3: 2 | E3: 3 | F3: 4 | G3: 5 | H3: 6 | I3: 7 | J3: 8 | K3: 9 | L3: 10 | M3: 11 | N3: 12 | O3: 13 | P3: 14 | Q3: 15 | R3: 16 | S3: 17 | T3: 18 | U3: 19 | V3: 20 | W3: 21 | X3: 22 | Y3: 23 | Z3: 24 | AA3: 25 | AB3: 26 | AC3: 27 | AD3: 28 | AE3: 29 | AF3: 30 | AG3: 31 | AH3: 32 | AI3: 33 | AJ3: 34 | AK3: 35 | AL3: 36
B4: Month starting | C4: =EDATE(Assumptions!$F$7,C3-1) | D4: =EDATE(Assumptions!$F$7,D3-1) | E4: =EDATE(Assumptions!$F$7,E3-1) | F4: =EDATE(Assumptions!$F$7,F3-1) | G4: =EDATE(Assumptions!$F$7,G3-1) | H4: =EDATE(Assumptions!$F$7,H3-1) | I4: =EDATE(Assumptions!$F$7,I3-1) | J4: =EDATE(Assumptions!$F$7,J3-1) | ... AL4: =EDATE(Assumptions!$F$7,AL3-1)
B5: Arena year | C5: =ROUNDUP(C3/12,0) | D5: =ROUNDUP(D3/12,0) | E5: =ROUNDUP(E3/12,0) | F5: =ROUNDUP(F3/12,0) | G5: =ROUNDUP(G3/12,0) | H5: =ROUNDUP(H3/12,0) | I5: =ROUNDUP(I3/12,0) | J5: =ROUNDUP(J3/12,0) | ... AL5: =ROUNDUP(AL3/12,0)
B6: Calendar month | C6: =MONTH(C4) | D6: =MONTH(D4) | E6: =MONTH(E4) | F6: =MONTH(F4) | G6: =MONTH(G4) | H6: =MONTH(H4) | I6: =MONTH(I4) | J6: =MONTH(J4) | ... AL6: =MONTH(AL4)
B8: MEMBERS
B9: Members | C9: =IF(C3<=12,Assumptions!$F$8+(Assumptions!$F$9-Assumptions!$F$8)*C3/12,IF(C3<=24,Assumptions!$F$9+(Assumptions!$F$10-Assumptions!$F$9)*(C3-12)/12,Assumptions!$F$10+(Assumptions!$F$11-Assumptions!$F$10)*(C3-24)/12)) | D9: =IF(D3<=12,Assumptions!$F$8+(Assumptions!$F$9-Assumptions!$F$8)*D3/12,IF(D3<=24,Assumptions!$F$9+(Assumptions!$F$10-Assumptions!$F$9)*(D3-12)/12,Assumptions!$F$10+(Assumptions!$F$11-Assumptions!$F$10)*(D3-24)/12)) | E9: =IF(E3<=12,Assumptions!$F$8+(Assumptions!$F$9-Assumptions!$F$8)*E3/12,IF(E3<=24,Assumptions!$F$9+(Assumptions!$F$10-Assumptions!$F$9)*(E3-12)/12,Assumptions!$F$10+(Assumptions!$F$11-Assumptions!$F$10)*(E3-24)/12)) | F9: =IF(F3<=12,Assumptions!$F$8+(Assumptions!$F$9-Assumptions!$F$8)*F3/12,IF(F3<=24,Assumptions!$F$9+(Assumptions!$F$10-Assumptions!$F$9)*(F3-12)/12,Assumptions!$F$10+(Assumptions!$F$11-Assumptions!$F$10)*(F3-24)/12)) | G9: =IF(G3<=12,Assumptions!$F$8+(Assumptions!$F$9-Assumptions!$F$8)*G3/12,IF(G3<=24,Assumptions!$F$9+(Assumptions!$F$10-Assumptions!$F$9)*(G3-12)/12,Assumptions!$F$10+(Assumptions!$F$11-Assumptions!$F$10)*(G3-24)/12)) | H9: =IF(H3<=12,Assumptions!$F$8+(Assumptions!$F$9-Assumptions!$F$8)*H3/12,IF(H3<=24,Assumptions!$F$9+(Assumptions!$F$10-Assumptions!$F$9)*(H3-12)/12,Assumptions!$F$10+(Assumptions!$F$11-Assumptions!$F$10)*(H3-24)/12)) | I9: =IF(I3<=12,Assumptions!$F$8+(Assumptions!$F$9-Assumptions!$F$8)*I3/12,IF(I3<=24,Assumptions!$F$9+(Assumptions!$F$10-Assumptions!$F$9)*(I3-12)/12,Assumptions!$F$10+(Assumptions!$F$11-Assumptions!$F$10)*(I3-24)/12)) | J9: =IF(J3<=12,Assumptions!$F$8+(Assumptions!$F$9-Assumptions!$F$8)*J3/12,IF(J3<=24,Assumptions!$F$9+(Assumptions!$F$10-Assumptions!$F$9)*(J3-12)/12,Assumptions!$F$10+(Assumptions!$F$11-Assumptions!$F$10)*(J3-24)/12)) | ... AL9: =IF(AL3<=12,Assumptions!$F$8+(Assumptions!$F$9-Assumptions!$F$8)*AL3/12,IF(AL3<=24,Assumptions!$F$9+(Assumptions!$F$10-Assumptions!$F$9)*(AL3-12)/12,Assumptions!$F$10+(Assumptions!$F$11-Assumptions!$F$10)*(AL3-24)/12))
B10: Of which on a 2-a-week plan | C10: =C9*Assumptions!$F$13 | D10: =D9*Assumptions!$F$13 | E10: =E9*Assumptions!$F$13 | F10: =F9*Assumptions!$F$13 | G10: =G9*Assumptions!$F$13 | H10: =H9*Assumptions!$F$13 | I10: =I9*Assumptions!$F$13 | J10: =J9*Assumptions!$F$13 | ... AL10: =AL9*Assumptions!$F$13
B11: Of which on a 3-a-week plan | C11: =C9*Assumptions!$F$15 | D11: =D9*Assumptions!$F$15 | E11: =E9*Assumptions!$F$15 | F11: =F9*Assumptions!$F$15 | G11: =G9*Assumptions!$F$15 | H11: =H9*Assumptions!$F$15 | I11: =I9*Assumptions!$F$15 | J11: =J9*Assumptions!$F$15 | ... AL11: =AL9*Assumptions!$F$15
B12: New joiners (growth + replacing leavers) | C12: =MAX(0,C9-Assumptions!$F$8)+Assumptions!$F$18*Assumptions!$F$8 | D12: =MAX(0,D9-C9)+Assumptions!$F$18*C9 | E12: =MAX(0,E9-D9)+Assumptions!$F$18*D9 | F12: =MAX(0,F9-E9)+Assumptions!$F$18*E9 | G12: =MAX(0,G9-F9)+Assumptions!$F$18*F9 | H12: =MAX(0,H9-G9)+Assumptions!$F$18*G9 | I12: =MAX(0,I9-H9)+Assumptions!$F$18*H9 | J12: =MAX(0,J9-I9)+Assumptions!$F$18*I9 | K12: =MAX(0,K9-J9)+Assumptions!$F$18*J9 | ... AL12: =MAX(0,AL9-AK9)+Assumptions!$F$18*AK9
B13: Class sessions a week | C13: =ROUNDUP((C9+C10+2*C11)/Assumptions!$F$19,0) | D13: =ROUNDUP((D9+D10+2*D11)/Assumptions!$F$19,0) | E13: =ROUNDUP((E9+E10+2*E11)/Assumptions!$F$19,0) | F13: =ROUNDUP((F9+F10+2*F11)/Assumptions!$F$19,0) | G13: =ROUNDUP((G9+G10+2*G11)/Assumptions!$F$19,0) | H13: =ROUNDUP((H9+H10+2*H11)/Assumptions!$F$19,0) | I13: =ROUNDUP((I9+I10+2*I11)/Assumptions!$F$19,0) | J13: =ROUNDUP((J9+J10+2*J11)/Assumptions!$F$19,0) | ... AL13: =ROUNDUP((AL9+AL10+2*AL11)/Assumptions!$F$19,0)
B15: INCOME (after Flat Rate VAT)
B16: Memberships | C16: =C9*Assumptions!$F$12*(1-Assumptions!$F$21) | D16: =D9*Assumptions!$F$12*(1-Assumptions!$F$21) | E16: =E9*Assumptions!$F$12*(1-Assumptions!$F$21) | F16: =F9*Assumptions!$F$12*(1-Assumptions!$F$21) | G16: =G9*Assumptions!$F$12*(1-Assumptions!$F$21) | H16: =H9*Assumptions!$F$12*(1-Assumptions!$F$21) | I16: =I9*Assumptions!$F$12*(1-Assumptions!$F$21) | J16: =J9*Assumptions!$F$12*(1-Assumptions!$F$21) | ... AL16: =AL9*Assumptions!$F$12*(1-Assumptions!$F$21)
B17: 2-a-week plans | C17: =C10*Assumptions!$F$14*(1-Assumptions!$F$21) | D17: =D10*Assumptions!$F$14*(1-Assumptions!$F$21) | E17: =E10*Assumptions!$F$14*(1-Assumptions!$F$21) | F17: =F10*Assumptions!$F$14*(1-Assumptions!$F$21) | G17: =G10*Assumptions!$F$14*(1-Assumptions!$F$21) | H17: =H10*Assumptions!$F$14*(1-Assumptions!$F$21) | I17: =I10*Assumptions!$F$14*(1-Assumptions!$F$21) | J17: =J10*Assumptions!$F$14*(1-Assumptions!$F$21) | ... AL17: =AL10*Assumptions!$F$14*(1-Assumptions!$F$21)
B18: 3-a-week plans | C18: =C11*Assumptions!$F$16*(1-Assumptions!$F$21) | D18: =D11*Assumptions!$F$16*(1-Assumptions!$F$21) | E18: =E11*Assumptions!$F$16*(1-Assumptions!$F$21) | F18: =F11*Assumptions!$F$16*(1-Assumptions!$F$21) | G18: =G11*Assumptions!$F$16*(1-Assumptions!$F$21) | H18: =H11*Assumptions!$F$16*(1-Assumptions!$F$21) | I18: =I11*Assumptions!$F$16*(1-Assumptions!$F$21) | J18: =J11*Assumptions!$F$16*(1-Assumptions!$F$21) | ... AL18: =AL11*Assumptions!$F$16*(1-Assumptions!$F$21)
B19: Joining fees | C19: =C12*Assumptions!$F$17*(1-Assumptions!$F$21) | D19: =D12*Assumptions!$F$17*(1-Assumptions!$F$21) | E19: =E12*Assumptions!$F$17*(1-Assumptions!$F$21) | F19: =F12*Assumptions!$F$17*(1-Assumptions!$F$21) | G19: =G12*Assumptions!$F$17*(1-Assumptions!$F$21) | H19: =H12*Assumptions!$F$17*(1-Assumptions!$F$21) | I19: =I12*Assumptions!$F$17*(1-Assumptions!$F$21) | J19: =J12*Assumptions!$F$17*(1-Assumptions!$F$21) | ... AL19: =AL12*Assumptions!$F$17*(1-Assumptions!$F$21)
B20: Birthday parties | C20: =CHOOSE(C$5,Assumptions!$F$32,Assumptions!$F$33,Assumptions!$F$34)*52/12*Assumptions!$F$31*(1-Assumptions!$F$21) | D20: =CHOOSE(D$5,Assumptions!$F$32,Assumptions!$F$33,Assumptions!$F$34)*52/12*Assumptions!$F$31*(1-Assumptions!$F$21) | E20: =CHOOSE(E$5,Assumptions!$F$32,Assumptions!$F$33,Assumptions!$F$34)*52/12*Assumptions!$F$31*(1-Assumptions!$F$21) | F20: =CHOOSE(F$5,Assumptions!$F$32,Assumptions!$F$33,Assumptions!$F$34)*52/12*Assumptions!$F$31*(1-Assumptions!$F$21) | G20: =CHOOSE(G$5,Assumptions!$F$32,Assumptions!$F$33,Assumptions!$F$34)*52/12*Assumptions!$F$31*(1-Assumptions!$F$21) | H20: =CHOOSE(H$5,Assumptions!$F$32,Assumptions!$F$33,Assumptions!$F$34)*52/12*Assumptions!$F$31*(1-Assumptions!$F$21) | I20: =CHOOSE(I$5,Assumptions!$F$32,Assumptions!$F$33,Assumptions!$F$34)*52/12*Assumptions!$F$31*(1-Assumptions!$F$21) | J20: =CHOOSE(J$5,Assumptions!$F$32,Assumptions!$F$33,Assumptions!$F$34)*52/12*Assumptions!$F$31*(1-Assumptions!$F$21) | ... AL20: =CHOOSE(AL$5,Assumptions!$F$32,Assumptions!$F$33,Assumptions!$F$34)*52/12*Assumptions!$F$31*(1-Assumptions!$F$21)
B21: 3x3 tournaments | C21: =CHOOSE(C$5,Assumptions!$F$39,Assumptions!$F$40,Assumptions!$F$41)/12*Assumptions!$F$42*Assumptions!$F$43*(1-Assumptions!$F$21) | D21: =CHOOSE(D$5,Assumptions!$F$39,Assumptions!$F$40,Assumptions!$F$41)/12*Assumptions!$F$42*Assumptions!$F$43*(1-Assumptions!$F$21) | E21: =CHOOSE(E$5,Assumptions!$F$39,Assumptions!$F$40,Assumptions!$F$41)/12*Assumptions!$F$42*Assumptions!$F$43*(1-Assumptions!$F$21) | F21: =CHOOSE(F$5,Assumptions!$F$39,Assumptions!$F$40,Assumptions!$F$41)/12*Assumptions!$F$42*Assumptions!$F$43*(1-Assumptions!$F$21) | G21: =CHOOSE(G$5,Assumptions!$F$39,Assumptions!$F$40,Assumptions!$F$41)/12*Assumptions!$F$42*Assumptions!$F$43*(1-Assumptions!$F$21) | H21: =CHOOSE(H$5,Assumptions!$F$39,Assumptions!$F$40,Assumptions!$F$41)/12*Assumptions!$F$42*Assumptions!$F$43*(1-Assumptions!$F$21) | I21: =CHOOSE(I$5,Assumptions!$F$39,Assumptions!$F$40,Assumptions!$F$41)/12*Assumptions!$F$42*Assumptions!$F$43*(1-Assumptions!$F$21) | J21: =CHOOSE(J$5,Assumptions!$F$39,Assumptions!$F$40,Assumptions!$F$41)/12*Assumptions!$F$42*Assumptions!$F$43*(1-Assumptions!$F$21) | ... AL21: =CHOOSE(AL$5,Assumptions!$F$39,Assumptions!$F$40,Assumptions!$F$41)/12*Assumptions!$F$42*Assumptions!$F$43*(1-Assumptions!$F$21)
B22: Holiday camps | C22: =INDEX(Assumptions!$C$106:$C$117,C$6)*5*CHOOSE(C$5,Assumptions!$F$48,Assumptions!$F$49,Assumptions!$F$50)*CHOOSE(C$5,Assumptions!$F$51,Assumptions!$F$52,Assumptions!$F$53)*Assumptions!$F$47*(1-Assumptions!$F$21) | D22: =INDEX(Assumptions!$C$106:$C$117,D$6)*5*CHOOSE(D$5,Assumptions!$F$48,Assumptions!$F$49,Assumptions!$F$50)*CHOOSE(D$5,Assumptions!$F$51,Assumptions!$F$52,Assumptions!$F$53)*Assumptions!$F$47*(1-Assumptions!$F$21) | E22: =INDEX(Assumptions!$C$106:$C$117,E$6)*5*CHOOSE(E$5,Assumptions!$F$48,Assumptions!$F$49,Assumptions!$F$50)*CHOOSE(E$5,Assumptions!$F$51,Assumptions!$F$52,Assumptions!$F$53)*Assumptions!$F$47*(1-Assumptions!$F$21) | F22: =INDEX(Assumptions!$C$106:$C$117,F$6)*5*CHOOSE(F$5,Assumptions!$F$48,Assumptions!$F$49,Assumptions!$F$50)*CHOOSE(F$5,Assumptions!$F$51,Assumptions!$F$52,Assumptions!$F$53)*Assumptions!$F$47*(1-Assumptions!$F$21) | G22: =INDEX(Assumptions!$C$106:$C$117,G$6)*5*CHOOSE(G$5,Assumptions!$F$48,Assumptions!$F$49,Assumptions!$F$50)*CHOOSE(G$5,Assumptions!$F$51,Assumptions!$F$52,Assumptions!$F$53)*Assumptions!$F$47*(1-Assumptions!$F$21) | H22: =INDEX(Assumptions!$C$106:$C$117,H$6)*5*CHOOSE(H$5,Assumptions!$F$48,Assumptions!$F$49,Assumptions!$F$50)*CHOOSE(H$5,Assumptions!$F$51,Assumptions!$F$52,Assumptions!$F$53)*Assumptions!$F$47*(1-Assumptions!$F$21) | I22: =INDEX(Assumptions!$C$106:$C$117,I$6)*5*CHOOSE(I$5,Assumptions!$F$48,Assumptions!$F$49,Assumptions!$F$50)*CHOOSE(I$5,Assumptions!$F$51,Assumptions!$F$52,Assumptions!$F$53)*Assumptions!$F$47*(1-Assumptions!$F$21) | J22: =INDEX(Assumptions!$C$106:$C$117,J$6)*5*CHOOSE(J$5,Assumptions!$F$48,Assumptions!$F$49,Assumptions!$F$50)*CHOOSE(J$5,Assumptions!$F$51,Assumptions!$F$52,Assumptions!$F$53)*Assumptions!$F$47*(1-Assumptions!$F$21) | ... AL22: =INDEX(Assumptions!$C$106:$C$117,AL$6)*5*CHOOSE(AL$5,Assumptions!$F$48,Assumptions!$F$49,Assumptions!$F$50)*CHOOSE(AL$5,Assumptions!$F$51,Assumptions!$F$52,Assumptions!$F$53)*Assumptions!$F$47*(1-Assumptions!$F$21)
B23: Funded holiday places (HAF) | C23: =INDEX(Assumptions!$D$106:$D$117,C$6)*Assumptions!$F$62*CHOOSE(C$5,Assumptions!$F$58,Assumptions!$F$59,Assumptions!$F$60)*Assumptions!$F$61 | D23: =INDEX(Assumptions!$D$106:$D$117,D$6)*Assumptions!$F$62*CHOOSE(D$5,Assumptions!$F$58,Assumptions!$F$59,Assumptions!$F$60)*Assumptions!$F$61 | E23: =INDEX(Assumptions!$D$106:$D$117,E$6)*Assumptions!$F$62*CHOOSE(E$5,Assumptions!$F$58,Assumptions!$F$59,Assumptions!$F$60)*Assumptions!$F$61 | F23: =INDEX(Assumptions!$D$106:$D$117,F$6)*Assumptions!$F$62*CHOOSE(F$5,Assumptions!$F$58,Assumptions!$F$59,Assumptions!$F$60)*Assumptions!$F$61 | G23: =INDEX(Assumptions!$D$106:$D$117,G$6)*Assumptions!$F$62*CHOOSE(G$5,Assumptions!$F$58,Assumptions!$F$59,Assumptions!$F$60)*Assumptions!$F$61 | H23: =INDEX(Assumptions!$D$106:$D$117,H$6)*Assumptions!$F$62*CHOOSE(H$5,Assumptions!$F$58,Assumptions!$F$59,Assumptions!$F$60)*Assumptions!$F$61 | I23: =INDEX(Assumptions!$D$106:$D$117,I$6)*Assumptions!$F$62*CHOOSE(I$5,Assumptions!$F$58,Assumptions!$F$59,Assumptions!$F$60)*Assumptions!$F$61 | J23: =INDEX(Assumptions!$D$106:$D$117,J$6)*Assumptions!$F$62*CHOOSE(J$5,Assumptions!$F$58,Assumptions!$F$59,Assumptions!$F$60)*Assumptions!$F$61 | ... AL23: =INDEX(Assumptions!$D$106:$D$117,AL$6)*Assumptions!$F$62*CHOOSE(AL$5,Assumptions!$F$58,Assumptions!$F$59,Assumptions!$F$60)*Assumptions!$F$61
B24: Breakfast All Stars | C24: =Assumptions!$F$66*Assumptions!$F$20/12*CHOOSE(C$5,Assumptions!$F$67,Assumptions!$F$68,Assumptions!$F$69)*Assumptions!$F$65*(1-Assumptions!$F$21) | D24: =Assumptions!$F$66*Assumptions!$F$20/12*CHOOSE(D$5,Assumptions!$F$67,Assumptions!$F$68,Assumptions!$F$69)*Assumptions!$F$65*(1-Assumptions!$F$21) | E24: =Assumptions!$F$66*Assumptions!$F$20/12*CHOOSE(E$5,Assumptions!$F$67,Assumptions!$F$68,Assumptions!$F$69)*Assumptions!$F$65*(1-Assumptions!$F$21) | F24: =Assumptions!$F$66*Assumptions!$F$20/12*CHOOSE(F$5,Assumptions!$F$67,Assumptions!$F$68,Assumptions!$F$69)*Assumptions!$F$65*(1-Assumptions!$F$21) | G24: =Assumptions!$F$66*Assumptions!$F$20/12*CHOOSE(G$5,Assumptions!$F$67,Assumptions!$F$68,Assumptions!$F$69)*Assumptions!$F$65*(1-Assumptions!$F$21) | H24: =Assumptions!$F$66*Assumptions!$F$20/12*CHOOSE(H$5,Assumptions!$F$67,Assumptions!$F$68,Assumptions!$F$69)*Assumptions!$F$65*(1-Assumptions!$F$21) | I24: =Assumptions!$F$66*Assumptions!$F$20/12*CHOOSE(I$5,Assumptions!$F$67,Assumptions!$F$68,Assumptions!$F$69)*Assumptions!$F$65*(1-Assumptions!$F$21) | J24: =Assumptions!$F$66*Assumptions!$F$20/12*CHOOSE(J$5,Assumptions!$F$67,Assumptions!$F$68,Assumptions!$F$69)*Assumptions!$F$65*(1-Assumptions!$F$21) | ... AL24: =Assumptions!$F$66*Assumptions!$F$20/12*CHOOSE(AL$5,Assumptions!$F$67,Assumptions!$F$68,Assumptions!$F$69)*Assumptions!$F$65*(1-Assumptions!$F$21)
B25: 3x3 leagues | C25: =CHOOSE(C$5,Assumptions!$F$74,Assumptions!$F$75,Assumptions!$F$76)*Assumptions!$F$72*Assumptions!$F$73/12*(1-Assumptions!$F$21) | D25: =CHOOSE(D$5,Assumptions!$F$74,Assumptions!$F$75,Assumptions!$F$76)*Assumptions!$F$72*Assumptions!$F$73/12*(1-Assumptions!$F$21) | E25: =CHOOSE(E$5,Assumptions!$F$74,Assumptions!$F$75,Assumptions!$F$76)*Assumptions!$F$72*Assumptions!$F$73/12*(1-Assumptions!$F$21) | F25: =CHOOSE(F$5,Assumptions!$F$74,Assumptions!$F$75,Assumptions!$F$76)*Assumptions!$F$72*Assumptions!$F$73/12*(1-Assumptions!$F$21) | G25: =CHOOSE(G$5,Assumptions!$F$74,Assumptions!$F$75,Assumptions!$F$76)*Assumptions!$F$72*Assumptions!$F$73/12*(1-Assumptions!$F$21) | H25: =CHOOSE(H$5,Assumptions!$F$74,Assumptions!$F$75,Assumptions!$F$76)*Assumptions!$F$72*Assumptions!$F$73/12*(1-Assumptions!$F$21) | I25: =CHOOSE(I$5,Assumptions!$F$74,Assumptions!$F$75,Assumptions!$F$76)*Assumptions!$F$72*Assumptions!$F$73/12*(1-Assumptions!$F$21) | J25: =CHOOSE(J$5,Assumptions!$F$74,Assumptions!$F$75,Assumptions!$F$76)*Assumptions!$F$72*Assumptions!$F$73/12*(1-Assumptions!$F$21) | ... AL25: =CHOOSE(AL$5,Assumptions!$F$74,Assumptions!$F$75,Assumptions!$F$76)*Assumptions!$F$72*Assumptions!$F$73/12*(1-Assumptions!$F$21)
B26: School PE support and CPD | C26: =CHOOSE(C$5,Assumptions!$F$79,Assumptions!$F$80,Assumptions!$F$81)/12*(1-Assumptions!$F$21) | D26: =CHOOSE(D$5,Assumptions!$F$79,Assumptions!$F$80,Assumptions!$F$81)/12*(1-Assumptions!$F$21) | E26: =CHOOSE(E$5,Assumptions!$F$79,Assumptions!$F$80,Assumptions!$F$81)/12*(1-Assumptions!$F$21) | F26: =CHOOSE(F$5,Assumptions!$F$79,Assumptions!$F$80,Assumptions!$F$81)/12*(1-Assumptions!$F$21) | G26: =CHOOSE(G$5,Assumptions!$F$79,Assumptions!$F$80,Assumptions!$F$81)/12*(1-Assumptions!$F$21) | H26: =CHOOSE(H$5,Assumptions!$F$79,Assumptions!$F$80,Assumptions!$F$81)/12*(1-Assumptions!$F$21) | I26: =CHOOSE(I$5,Assumptions!$F$79,Assumptions!$F$80,Assumptions!$F$81)/12*(1-Assumptions!$F$21) | J26: =CHOOSE(J$5,Assumptions!$F$79,Assumptions!$F$80,Assumptions!$F$81)/12*(1-Assumptions!$F$21) | ... AL26: =CHOOSE(AL$5,Assumptions!$F$79,Assumptions!$F$80,Assumptions!$F$81)/12*(1-Assumptions!$F$21)
B27: Hire of unused hours | C27: =CHOOSE(C$5,Assumptions!$F$82,Assumptions!$F$83,Assumptions!$F$84)/12*(1-Assumptions!$F$21) | D27: =CHOOSE(D$5,Assumptions!$F$82,Assumptions!$F$83,Assumptions!$F$84)/12*(1-Assumptions!$F$21) | E27: =CHOOSE(E$5,Assumptions!$F$82,Assumptions!$F$83,Assumptions!$F$84)/12*(1-Assumptions!$F$21) | F27: =CHOOSE(F$5,Assumptions!$F$82,Assumptions!$F$83,Assumptions!$F$84)/12*(1-Assumptions!$F$21) | G27: =CHOOSE(G$5,Assumptions!$F$82,Assumptions!$F$83,Assumptions!$F$84)/12*(1-Assumptions!$F$21) | H27: =CHOOSE(H$5,Assumptions!$F$82,Assumptions!$F$83,Assumptions!$F$84)/12*(1-Assumptions!$F$21) | I27: =CHOOSE(I$5,Assumptions!$F$82,Assumptions!$F$83,Assumptions!$F$84)/12*(1-Assumptions!$F$21) | J27: =CHOOSE(J$5,Assumptions!$F$82,Assumptions!$F$83,Assumptions!$F$84)/12*(1-Assumptions!$F$21) | ... AL27: =CHOOSE(AL$5,Assumptions!$F$82,Assumptions!$F$83,Assumptions!$F$84)/12*(1-Assumptions!$F$21)
B28: Grants for community sessions | C28: =Assumptions!$F$86*Assumptions!$F$20/12*Assumptions!$F$28*CHOOSE(C$5,Assumptions!$F$87,Assumptions!$F$88,Assumptions!$F$89) | D28: =Assumptions!$F$86*Assumptions!$F$20/12*Assumptions!$F$28*CHOOSE(D$5,Assumptions!$F$87,Assumptions!$F$88,Assumptions!$F$89) | E28: =Assumptions!$F$86*Assumptions!$F$20/12*Assumptions!$F$28*CHOOSE(E$5,Assumptions!$F$87,Assumptions!$F$88,Assumptions!$F$89) | F28: =Assumptions!$F$86*Assumptions!$F$20/12*Assumptions!$F$28*CHOOSE(F$5,Assumptions!$F$87,Assumptions!$F$88,Assumptions!$F$89) | G28: =Assumptions!$F$86*Assumptions!$F$20/12*Assumptions!$F$28*CHOOSE(G$5,Assumptions!$F$87,Assumptions!$F$88,Assumptions!$F$89) | H28: =Assumptions!$F$86*Assumptions!$F$20/12*Assumptions!$F$28*CHOOSE(H$5,Assumptions!$F$87,Assumptions!$F$88,Assumptions!$F$89) | I28: =Assumptions!$F$86*Assumptions!$F$20/12*Assumptions!$F$28*CHOOSE(I$5,Assumptions!$F$87,Assumptions!$F$88,Assumptions!$F$89) | J28: =Assumptions!$F$86*Assumptions!$F$20/12*Assumptions!$F$28*CHOOSE(J$5,Assumptions!$F$87,Assumptions!$F$88,Assumptions!$F$89) | ... AL28: =Assumptions!$F$86*Assumptions!$F$20/12*Assumptions!$F$28*CHOOSE(AL$5,Assumptions!$F$87,Assumptions!$F$88,Assumptions!$F$89)
B29: Total income | C29: =SUM(C16:C28) | D29: =SUM(D16:D28) | E29: =SUM(E16:E28) | F29: =SUM(F16:F28) | G29: =SUM(G16:G28) | H29: =SUM(H16:H28) | I29: =SUM(I16:I28) | J29: =SUM(J16:J28) | ... AL29: =SUM(AL16:AL28)
B31: DIRECT COSTS
B32: Class coaching | C32: =C13*Assumptions!$F$20/12*Assumptions!$F$28 | D32: =D13*Assumptions!$F$20/12*Assumptions!$F$28 | E32: =E13*Assumptions!$F$20/12*Assumptions!$F$28 | F32: =F13*Assumptions!$F$20/12*Assumptions!$F$28 | G32: =G13*Assumptions!$F$20/12*Assumptions!$F$28 | H32: =H13*Assumptions!$F$20/12*Assumptions!$F$28 | I32: =I13*Assumptions!$F$20/12*Assumptions!$F$28 | J32: =J13*Assumptions!$F$20/12*Assumptions!$F$28 | ... AL32: =AL13*Assumptions!$F$20/12*Assumptions!$F$28
B33: Party staff and extras | C33: =CHOOSE(C$5,Assumptions!$F$32,Assumptions!$F$33,Assumptions!$F$34)*52/12*(Assumptions!$F$35*(Assumptions!$F$24+Assumptions!$F$25)*(1+Assumptions!$F$27)+Assumptions!$F$36) | D33: =CHOOSE(D$5,Assumptions!$F$32,Assumptions!$F$33,Assumptions!$F$34)*52/12*(Assumptions!$F$35*(Assumptions!$F$24+Assumptions!$F$25)*(1+Assumptions!$F$27)+Assumptions!$F$36) | E33: =CHOOSE(E$5,Assumptions!$F$32,Assumptions!$F$33,Assumptions!$F$34)*52/12*(Assumptions!$F$35*(Assumptions!$F$24+Assumptions!$F$25)*(1+Assumptions!$F$27)+Assumptions!$F$36) | F33: =CHOOSE(F$5,Assumptions!$F$32,Assumptions!$F$33,Assumptions!$F$34)*52/12*(Assumptions!$F$35*(Assumptions!$F$24+Assumptions!$F$25)*(1+Assumptions!$F$27)+Assumptions!$F$36) | G33: =CHOOSE(G$5,Assumptions!$F$32,Assumptions!$F$33,Assumptions!$F$34)*52/12*(Assumptions!$F$35*(Assumptions!$F$24+Assumptions!$F$25)*(1+Assumptions!$F$27)+Assumptions!$F$36) | H33: =CHOOSE(H$5,Assumptions!$F$32,Assumptions!$F$33,Assumptions!$F$34)*52/12*(Assumptions!$F$35*(Assumptions!$F$24+Assumptions!$F$25)*(1+Assumptions!$F$27)+Assumptions!$F$36) | I33: =CHOOSE(I$5,Assumptions!$F$32,Assumptions!$F$33,Assumptions!$F$34)*52/12*(Assumptions!$F$35*(Assumptions!$F$24+Assumptions!$F$25)*(1+Assumptions!$F$27)+Assumptions!$F$36) | J33: =CHOOSE(J$5,Assumptions!$F$32,Assumptions!$F$33,Assumptions!$F$34)*52/12*(Assumptions!$F$35*(Assumptions!$F$24+Assumptions!$F$25)*(1+Assumptions!$F$27)+Assumptions!$F$36) | ... AL33: =CHOOSE(AL$5,Assumptions!$F$32,Assumptions!$F$33,Assumptions!$F$34)*52/12*(Assumptions!$F$35*(Assumptions!$F$24+Assumptions!$F$25)*(1+Assumptions!$F$27)+Assumptions!$F$36)
B34: Tournament staff and medals | C34: =CHOOSE(C$5,Assumptions!$F$39,Assumptions!$F$40,Assumptions!$F$41)/12*(Assumptions!$F$44*Assumptions!$F$56+Assumptions!$F$42*Assumptions!$F$45) | D34: =CHOOSE(D$5,Assumptions!$F$39,Assumptions!$F$40,Assumptions!$F$41)/12*(Assumptions!$F$44*Assumptions!$F$56+Assumptions!$F$42*Assumptions!$F$45) | E34: =CHOOSE(E$5,Assumptions!$F$39,Assumptions!$F$40,Assumptions!$F$41)/12*(Assumptions!$F$44*Assumptions!$F$56+Assumptions!$F$42*Assumptions!$F$45) | F34: =CHOOSE(F$5,Assumptions!$F$39,Assumptions!$F$40,Assumptions!$F$41)/12*(Assumptions!$F$44*Assumptions!$F$56+Assumptions!$F$42*Assumptions!$F$45) | G34: =CHOOSE(G$5,Assumptions!$F$39,Assumptions!$F$40,Assumptions!$F$41)/12*(Assumptions!$F$44*Assumptions!$F$56+Assumptions!$F$42*Assumptions!$F$45) | H34: =CHOOSE(H$5,Assumptions!$F$39,Assumptions!$F$40,Assumptions!$F$41)/12*(Assumptions!$F$44*Assumptions!$F$56+Assumptions!$F$42*Assumptions!$F$45) | I34: =CHOOSE(I$5,Assumptions!$F$39,Assumptions!$F$40,Assumptions!$F$41)/12*(Assumptions!$F$44*Assumptions!$F$56+Assumptions!$F$42*Assumptions!$F$45) | J34: =CHOOSE(J$5,Assumptions!$F$39,Assumptions!$F$40,Assumptions!$F$41)/12*(Assumptions!$F$44*Assumptions!$F$56+Assumptions!$F$42*Assumptions!$F$45) | ... AL34: =CHOOSE(AL$5,Assumptions!$F$39,Assumptions!$F$40,Assumptions!$F$41)/12*(Assumptions!$F$44*Assumptions!$F$56+Assumptions!$F$42*Assumptions!$F$45)
B35: Camp staff | C35: =INDEX(Assumptions!$C$106:$C$117,C$6)*5*CHOOSE(C$5,Assumptions!$F$48,Assumptions!$F$49,Assumptions!$F$50)*ROUNDUP(CHOOSE(C$5,Assumptions!$F$51,Assumptions!$F$52,Assumptions!$F$53)/Assumptions!$F$54,0)*Assumptions!$F$55*Assumptions!$F$56 | D35: =INDEX(Assumptions!$C$106:$C$117,D$6)*5*CHOOSE(D$5,Assumptions!$F$48,Assumptions!$F$49,Assumptions!$F$50)*ROUNDUP(CHOOSE(D$5,Assumptions!$F$51,Assumptions!$F$52,Assumptions!$F$53)/Assumptions!$F$54,0)*Assumptions!$F$55*Assumptions!$F$56 | E35: =INDEX(Assumptions!$C$106:$C$117,E$6)*5*CHOOSE(E$5,Assumptions!$F$48,Assumptions!$F$49,Assumptions!$F$50)*ROUNDUP(CHOOSE(E$5,Assumptions!$F$51,Assumptions!$F$52,Assumptions!$F$53)/Assumptions!$F$54,0)*Assumptions!$F$55*Assumptions!$F$56 | F35: =INDEX(Assumptions!$C$106:$C$117,F$6)*5*CHOOSE(F$5,Assumptions!$F$48,Assumptions!$F$49,Assumptions!$F$50)*ROUNDUP(CHOOSE(F$5,Assumptions!$F$51,Assumptions!$F$52,Assumptions!$F$53)/Assumptions!$F$54,0)*Assumptions!$F$55*Assumptions!$F$56 | G35: =INDEX(Assumptions!$C$106:$C$117,G$6)*5*CHOOSE(G$5,Assumptions!$F$48,Assumptions!$F$49,Assumptions!$F$50)*ROUNDUP(CHOOSE(G$5,Assumptions!$F$51,Assumptions!$F$52,Assumptions!$F$53)/Assumptions!$F$54,0)*Assumptions!$F$55*Assumptions!$F$56 | H35: =INDEX(Assumptions!$C$106:$C$117,H$6)*5*CHOOSE(H$5,Assumptions!$F$48,Assumptions!$F$49,Assumptions!$F$50)*ROUNDUP(CHOOSE(H$5,Assumptions!$F$51,Assumptions!$F$52,Assumptions!$F$53)/Assumptions!$F$54,0)*Assumptions!$F$55*Assumptions!$F$56 | I35: =INDEX(Assumptions!$C$106:$C$117,I$6)*5*CHOOSE(I$5,Assumptions!$F$48,Assumptions!$F$49,Assumptions!$F$50)*ROUNDUP(CHOOSE(I$5,Assumptions!$F$51,Assumptions!$F$52,Assumptions!$F$53)/Assumptions!$F$54,0)*Assumptions!$F$55*Assumptions!$F$56 | J35: =INDEX(Assumptions!$C$106:$C$117,J$6)*5*CHOOSE(J$5,Assumptions!$F$48,Assumptions!$F$49,Assumptions!$F$50)*ROUNDUP(CHOOSE(J$5,Assumptions!$F$51,Assumptions!$F$52,Assumptions!$F$53)/Assumptions!$F$54,0)*Assumptions!$F$55*Assumptions!$F$56 | ... AL35: =INDEX(Assumptions!$C$106:$C$117,AL$6)*5*CHOOSE(AL$5,Assumptions!$F$48,Assumptions!$F$49,Assumptions!$F$50)*ROUNDUP(CHOOSE(AL$5,Assumptions!$F$51,Assumptions!$F$52,Assumptions!$F$53)/Assumptions!$F$54,0)*Assumptions!$F$55*Assumptions!$F$56
B36: Funded places: food and extra staff | C36: =INDEX(Assumptions!$D$106:$D$117,C$6)*Assumptions!$F$62*CHOOSE(C$5,Assumptions!$F$58,Assumptions!$F$59,Assumptions!$F$60)*Assumptions!$F$63 | D36: =INDEX(Assumptions!$D$106:$D$117,D$6)*Assumptions!$F$62*CHOOSE(D$5,Assumptions!$F$58,Assumptions!$F$59,Assumptions!$F$60)*Assumptions!$F$63 | E36: =INDEX(Assumptions!$D$106:$D$117,E$6)*Assumptions!$F$62*CHOOSE(E$5,Assumptions!$F$58,Assumptions!$F$59,Assumptions!$F$60)*Assumptions!$F$63 | F36: =INDEX(Assumptions!$D$106:$D$117,F$6)*Assumptions!$F$62*CHOOSE(F$5,Assumptions!$F$58,Assumptions!$F$59,Assumptions!$F$60)*Assumptions!$F$63 | G36: =INDEX(Assumptions!$D$106:$D$117,G$6)*Assumptions!$F$62*CHOOSE(G$5,Assumptions!$F$58,Assumptions!$F$59,Assumptions!$F$60)*Assumptions!$F$63 | H36: =INDEX(Assumptions!$D$106:$D$117,H$6)*Assumptions!$F$62*CHOOSE(H$5,Assumptions!$F$58,Assumptions!$F$59,Assumptions!$F$60)*Assumptions!$F$63 | I36: =INDEX(Assumptions!$D$106:$D$117,I$6)*Assumptions!$F$62*CHOOSE(I$5,Assumptions!$F$58,Assumptions!$F$59,Assumptions!$F$60)*Assumptions!$F$63 | J36: =INDEX(Assumptions!$D$106:$D$117,J$6)*Assumptions!$F$62*CHOOSE(J$5,Assumptions!$F$58,Assumptions!$F$59,Assumptions!$F$60)*Assumptions!$F$63 | ... AL36: =INDEX(Assumptions!$D$106:$D$117,AL$6)*Assumptions!$F$62*CHOOSE(AL$5,Assumptions!$F$58,Assumptions!$F$59,Assumptions!$F$60)*Assumptions!$F$63
B37: Breakfast coaching | C37: =Assumptions!$F$66*Assumptions!$F$20/12*Assumptions!$F$24*Assumptions!$F$70*(1+Assumptions!$F$27)*(CHOOSE(C$5,Assumptions!$F$67,Assumptions!$F$68,Assumptions!$F$69)>0) | D37: =Assumptions!$F$66*Assumptions!$F$20/12*Assumptions!$F$24*Assumptions!$F$70*(1+Assumptions!$F$27)*(CHOOSE(D$5,Assumptions!$F$67,Assumptions!$F$68,Assumptions!$F$69)>0) | E37: =Assumptions!$F$66*Assumptions!$F$20/12*Assumptions!$F$24*Assumptions!$F$70*(1+Assumptions!$F$27)*(CHOOSE(E$5,Assumptions!$F$67,Assumptions!$F$68,Assumptions!$F$69)>0) | F37: =Assumptions!$F$66*Assumptions!$F$20/12*Assumptions!$F$24*Assumptions!$F$70*(1+Assumptions!$F$27)*(CHOOSE(F$5,Assumptions!$F$67,Assumptions!$F$68,Assumptions!$F$69)>0) | G37: =Assumptions!$F$66*Assumptions!$F$20/12*Assumptions!$F$24*Assumptions!$F$70*(1+Assumptions!$F$27)*(CHOOSE(G$5,Assumptions!$F$67,Assumptions!$F$68,Assumptions!$F$69)>0) | H37: =Assumptions!$F$66*Assumptions!$F$20/12*Assumptions!$F$24*Assumptions!$F$70*(1+Assumptions!$F$27)*(CHOOSE(H$5,Assumptions!$F$67,Assumptions!$F$68,Assumptions!$F$69)>0) | I37: =Assumptions!$F$66*Assumptions!$F$20/12*Assumptions!$F$24*Assumptions!$F$70*(1+Assumptions!$F$27)*(CHOOSE(I$5,Assumptions!$F$67,Assumptions!$F$68,Assumptions!$F$69)>0) | J37: =Assumptions!$F$66*Assumptions!$F$20/12*Assumptions!$F$24*Assumptions!$F$70*(1+Assumptions!$F$27)*(CHOOSE(J$5,Assumptions!$F$67,Assumptions!$F$68,Assumptions!$F$69)>0) | ... AL37: =Assumptions!$F$66*Assumptions!$F$20/12*Assumptions!$F$24*Assumptions!$F$70*(1+Assumptions!$F$27)*(CHOOSE(AL$5,Assumptions!$F$67,Assumptions!$F$68,Assumptions!$F$69)>0)
B38: League coaching | C38: =Assumptions!$F$77*Assumptions!$F$20/12*Assumptions!$F$28*(CHOOSE(C$5,Assumptions!$F$74,Assumptions!$F$75,Assumptions!$F$76)>0) | D38: =Assumptions!$F$77*Assumptions!$F$20/12*Assumptions!$F$28*(CHOOSE(D$5,Assumptions!$F$74,Assumptions!$F$75,Assumptions!$F$76)>0) | E38: =Assumptions!$F$77*Assumptions!$F$20/12*Assumptions!$F$28*(CHOOSE(E$5,Assumptions!$F$74,Assumptions!$F$75,Assumptions!$F$76)>0) | F38: =Assumptions!$F$77*Assumptions!$F$20/12*Assumptions!$F$28*(CHOOSE(F$5,Assumptions!$F$74,Assumptions!$F$75,Assumptions!$F$76)>0) | G38: =Assumptions!$F$77*Assumptions!$F$20/12*Assumptions!$F$28*(CHOOSE(G$5,Assumptions!$F$74,Assumptions!$F$75,Assumptions!$F$76)>0) | H38: =Assumptions!$F$77*Assumptions!$F$20/12*Assumptions!$F$28*(CHOOSE(H$5,Assumptions!$F$74,Assumptions!$F$75,Assumptions!$F$76)>0) | I38: =Assumptions!$F$77*Assumptions!$F$20/12*Assumptions!$F$28*(CHOOSE(I$5,Assumptions!$F$74,Assumptions!$F$75,Assumptions!$F$76)>0) | J38: =Assumptions!$F$77*Assumptions!$F$20/12*Assumptions!$F$28*(CHOOSE(J$5,Assumptions!$F$74,Assumptions!$F$75,Assumptions!$F$76)>0) | ... AL38: =Assumptions!$F$77*Assumptions!$F$20/12*Assumptions!$F$28*(CHOOSE(AL$5,Assumptions!$F$74,Assumptions!$F$75,Assumptions!$F$76)>0)
B39: Community session coaching | C39: =Assumptions!$F$86*Assumptions!$F$20/12*Assumptions!$F$28 | D39: =Assumptions!$F$86*Assumptions!$F$20/12*Assumptions!$F$28 | E39: =Assumptions!$F$86*Assumptions!$F$20/12*Assumptions!$F$28 | F39: =Assumptions!$F$86*Assumptions!$F$20/12*Assumptions!$F$28 | G39: =Assumptions!$F$86*Assumptions!$F$20/12*Assumptions!$F$28 | H39: =Assumptions!$F$86*Assumptions!$F$20/12*Assumptions!$F$28 | I39: =Assumptions!$F$86*Assumptions!$F$20/12*Assumptions!$F$28 | J39: =Assumptions!$F$86*Assumptions!$F$20/12*Assumptions!$F$28 | ... AL39: =Assumptions!$F$86*Assumptions!$F$20/12*Assumptions!$F$28
B40: Card and payment fees | C40: =SUM(C16:C22,C24:C25)/(1-Assumptions!$F$21)*Assumptions!$F$22 | D40: =SUM(D16:D22,D24:D25)/(1-Assumptions!$F$21)*Assumptions!$F$22 | E40: =SUM(E16:E22,E24:E25)/(1-Assumptions!$F$21)*Assumptions!$F$22 | F40: =SUM(F16:F22,F24:F25)/(1-Assumptions!$F$21)*Assumptions!$F$22 | G40: =SUM(G16:G22,G24:G25)/(1-Assumptions!$F$21)*Assumptions!$F$22 | H40: =SUM(H16:H22,H24:H25)/(1-Assumptions!$F$21)*Assumptions!$F$22 | I40: =SUM(I16:I22,I24:I25)/(1-Assumptions!$F$21)*Assumptions!$F$22 | J40: =SUM(J16:J22,J24:J25)/(1-Assumptions!$F$21)*Assumptions!$F$22 | ... AL40: =SUM(AL16:AL22,AL24:AL25)/(1-Assumptions!$F$21)*Assumptions!$F$22
B41: Total direct costs | C41: =SUM(C32:C40) | D41: =SUM(D32:D40) | E41: =SUM(E32:E40) | F41: =SUM(F32:F40) | G41: =SUM(G32:G40) | H41: =SUM(H32:H40) | I41: =SUM(I32:I40) | J41: =SUM(J32:J40) | ... AL41: =SUM(AL32:AL40)
B43: Contribution after direct costs | C43: =C29-C41 | D43: =D29-D41 | E43: =E29-E41 | F43: =F29-F41 | G43: =G29-G41 | H43: =H29-H41 | I43: =I29-I41 | J43: =J29-J41 | ... AL43: =AL29-AL41
B45: ARENA COSTS
B46: Supplier finance (Zappshelter package) | C46: =Assumptions!$F$91*(C3<=Assumptions!$F$92) | D46: =Assumptions!$F$91*(D3<=Assumptions!$F$92) | E46: =Assumptions!$F$91*(E3<=Assumptions!$F$92) | F46: =Assumptions!$F$91*(F3<=Assumptions!$F$92) | G46: =Assumptions!$F$91*(G3<=Assumptions!$F$92) | H46: =Assumptions!$F$91*(H3<=Assumptions!$F$92) | I46: =Assumptions!$F$91*(I3<=Assumptions!$F$92) | J46: =Assumptions!$F$91*(J3<=Assumptions!$F$92) | ... AL46: =Assumptions!$F$91*(AL3<=Assumptions!$F$92)
B47: Running: insurance, power, maintenance | C47: =Assumptions!$F$93 | D47: =Assumptions!$F$93 | E47: =Assumptions!$F$93 | F47: =Assumptions!$F$93 | G47: =Assumptions!$F$93 | H47: =Assumptions!$F$93 | I47: =Assumptions!$F$93 | J47: =Assumptions!$F$93 | ... AL47: =Assumptions!$F$93
B48: Heating (winter months) | C48: =Assumptions!$F$94/SUM(Assumptions!$E$106:$E$117)*INDEX(Assumptions!$E$106:$E$117,C$6) | D48: =Assumptions!$F$94/SUM(Assumptions!$E$106:$E$117)*INDEX(Assumptions!$E$106:$E$117,D$6) | E48: =Assumptions!$F$94/SUM(Assumptions!$E$106:$E$117)*INDEX(Assumptions!$E$106:$E$117,E$6) | F48: =Assumptions!$F$94/SUM(Assumptions!$E$106:$E$117)*INDEX(Assumptions!$E$106:$E$117,F$6) | G48: =Assumptions!$F$94/SUM(Assumptions!$E$106:$E$117)*INDEX(Assumptions!$E$106:$E$117,G$6) | H48: =Assumptions!$F$94/SUM(Assumptions!$E$106:$E$117)*INDEX(Assumptions!$E$106:$E$117,H$6) | I48: =Assumptions!$F$94/SUM(Assumptions!$E$106:$E$117)*INDEX(Assumptions!$E$106:$E$117,I$6) | J48: =Assumptions!$F$94/SUM(Assumptions!$E$106:$E$117)*INDEX(Assumptions!$E$106:$E$117,J$6) | ... AL48: =Assumptions!$F$94/SUM(Assumptions!$E$106:$E$117)*INDEX(Assumptions!$E$106:$E$117,AL$6)
B49: Rent to the school | C49: =Assumptions!$F$95 | D49: =Assumptions!$F$95 | E49: =Assumptions!$F$95 | F49: =Assumptions!$F$95 | G49: =Assumptions!$F$95 | H49: =Assumptions!$F$95 | I49: =Assumptions!$F$95 | J49: =Assumptions!$F$95 | ... AL49: =Assumptions!$F$95
B50: Marketing | C50: =Assumptions!$F$96 | D50: =Assumptions!$F$96 | E50: =Assumptions!$F$96 | F50: =Assumptions!$F$96 | G50: =Assumptions!$F$96 | H50: =Assumptions!$F$96 | I50: =Assumptions!$F$96 | J50: =Assumptions!$F$96 | ... AL50: =Assumptions!$F$96
B51: Admin and systems | C51: =Assumptions!$F$97 | D51: =Assumptions!$F$97 | E51: =Assumptions!$F$97 | F51: =Assumptions!$F$97 | G51: =Assumptions!$F$97 | H51: =Assumptions!$F$97 | I51: =Assumptions!$F$97 | J51: =Assumptions!$F$97 | ... AL51: =Assumptions!$F$97
B52: Kit replacement | C52: =Assumptions!$F$98/12 | D52: =Assumptions!$F$98/12 | E52: =Assumptions!$F$98/12 | F52: =Assumptions!$F$98/12 | G52: =Assumptions!$F$98/12 | H52: =Assumptions!$F$98/12 | I52: =Assumptions!$F$98/12 | J52: =Assumptions!$F$98/12 | ... AL52: =Assumptions!$F$98/12
B53: Total Arena costs | C53: =SUM(C46:C52) | D53: =SUM(D46:D52) | E53: =SUM(E46:E52) | F53: =SUM(F46:F52) | G53: =SUM(G46:G52) | H53: =SUM(H46:H52) | I53: =SUM(I46:I52) | J53: =SUM(J46:J52) | ... AL53: =SUM(AL46:AL52)
B55: SITE PROFIT (before central overheads) | C55: =C43-C53 | D55: =D43-D53 | E55: =E43-E53 | F55: =F43-F53 | G55: =G43-G53 | H55: =H43-H53 | I55: =I43-I53 | J55: =J43-J53 | ... AL55: =AL43-AL53
B56: Cumulative site profit | C56: =C55 | D56: =C56+D55 | E56: =D56+E55 | F56: =E56+F55 | G56: =F56+G55 | H56: =G56+H55 | I56: =H56+I55 | J56: =I56+J55 | K56: =J56+K55 | ... AL56: =AK56+AL55
B58: CAPACITY
B59: Court hours used a week (classes, community, leagues, parties) | C59: =C13+Assumptions!$F$86+Assumptions!$F$77*(CHOOSE(C$5,Assumptions!$F$74,Assumptions!$F$75,Assumptions!$F$76)>0)+CHOOSE(C$5,Assumptions!$F$32,Assumptions!$F$33,Assumptions!$F$34)*Assumptions!$F$37 | D59: =D13+Assumptions!$F$86+Assumptions!$F$77*(CHOOSE(D$5,Assumptions!$F$74,Assumptions!$F$75,Assumptions!$F$76)>0)+CHOOSE(D$5,Assumptions!$F$32,Assumptions!$F$33,Assumptions!$F$34)*Assumptions!$F$37 | E59: =E13+Assumptions!$F$86+Assumptions!$F$77*(CHOOSE(E$5,Assumptions!$F$74,Assumptions!$F$75,Assumptions!$F$76)>0)+CHOOSE(E$5,Assumptions!$F$32,Assumptions!$F$33,Assumptions!$F$34)*Assumptions!$F$37 | F59: =F13+Assumptions!$F$86+Assumptions!$F$77*(CHOOSE(F$5,Assumptions!$F$74,Assumptions!$F$75,Assumptions!$F$76)>0)+CHOOSE(F$5,Assumptions!$F$32,Assumptions!$F$33,Assumptions!$F$34)*Assumptions!$F$37 | G59: =G13+Assumptions!$F$86+Assumptions!$F$77*(CHOOSE(G$5,Assumptions!$F$74,Assumptions!$F$75,Assumptions!$F$76)>0)+CHOOSE(G$5,Assumptions!$F$32,Assumptions!$F$33,Assumptions!$F$34)*Assumptions!$F$37 | H59: =H13+Assumptions!$F$86+Assumptions!$F$77*(CHOOSE(H$5,Assumptions!$F$74,Assumptions!$F$75,Assumptions!$F$76)>0)+CHOOSE(H$5,Assumptions!$F$32,Assumptions!$F$33,Assumptions!$F$34)*Assumptions!$F$37 | I59: =I13+Assumptions!$F$86+Assumptions!$F$77*(CHOOSE(I$5,Assumptions!$F$74,Assumptions!$F$75,Assumptions!$F$76)>0)+CHOOSE(I$5,Assumptions!$F$32,Assumptions!$F$33,Assumptions!$F$34)*Assumptions!$F$37 | J59: =J13+Assumptions!$F$86+Assumptions!$F$77*(CHOOSE(J$5,Assumptions!$F$74,Assumptions!$F$75,Assumptions!$F$76)>0)+CHOOSE(J$5,Assumptions!$F$32,Assumptions!$F$33,Assumptions!$F$34)*Assumptions!$F$37 | ... AL59: =AL13+Assumptions!$F$86+Assumptions!$F$77*(CHOOSE(AL$5,Assumptions!$F$74,Assumptions!$F$75,Assumptions!$F$76)>0)+CHOOSE(AL$5,Assumptions!$F$32,Assumptions!$F$33,Assumptions!$F$34)*Assumptions!$F$37
B60: Share of usable court hours | C60: =C59/Assumptions!$F$29 | D60: =D59/Assumptions!$F$29 | E60: =E59/Assumptions!$F$29 | F60: =F59/Assumptions!$F$29 | G60: =G59/Assumptions!$F$29 | H60: =H59/Assumptions!$F$29 | I60: =I59/Assumptions!$F$29 | J60: =J59/Assumptions!$F$29 | ... AL60: =AL59/Assumptions!$F$29

Sheet Build and funding
A1: Heroes Arena: build cost and how it is paid for
A2: Ex VAT unless stated. A floor, not a budget: formal quotes still needed (Project Overview v0.2, cost sheet v6.6).
A4: Item | B4: Low £ | C4: High £ | D4: Middle £ | E4: Source / label
A5: Zappshelter package: 17 × 12.2 m canopy, branded covers, end walls, roller door, fire door, install | B5: 87343 | C5: 87343 | D5: =AVERAGE(B5:C5) | E5: Quote: Zappshelter, Peter Laird, 29 Oct 2026 (includes container mounting kit and plant hire)
A6: Containers: 40 ft reception + 2 × 20 ft stores | B6: 8600 | C6: 12000 | D6: =AVERAGE(B6:C6) | E6: Indicative low: Zappshelter 29 Oct, 2 × 40 ft at about £4,300 each delivered (rental option £112/month each). High: desk estimate for converted units
A7: Reception fit-out and accessible WC | B7: 12000 | C7: 20000 | D7: =AVERAGE(B7:C7) | E7: Placeholder: unpriced (new spec, 29 Oct 2026)
A8: Court tiles, custom multi-sport, 15.0 × 10.2 m | B8: 6250 | C8: 6250 | D8: =AVERAGE(B8:C8) | E8: Quote: Net World Sports Q00129975, 28 Oct 2026 (logo, edging, basketball, pickleball and badminton lines). Shipping to confirm
A9: Run-off tiles | B9: 2552 | C9: 3358 | D9: =AVERAGE(B9:C9) | E9: Desk estimate, cost sheet v6.6
A10: Three movable hoops | B10: 4000 | C10: 4000 | D10: =AVERAGE(B10:C10) | E10: Jamie assumption, 28 Oct 2026
A11: LED lighting and electrics | B11: 3650 | C11: 6650 | D11: =AVERAGE(B11:C11) | E11: Electrician £650 (desk) + lighting placeholder £3k–£6k
A12: Multi-sport kit and sports wheelchairs | B12: 3000 | C12: 8000 | D12: =AVERAGE(B12:C12) | E12: Placeholder: nets, paddles, dodgeballs, 2–4 sports wheelchairs
A13: Planning, structural and safety fees | B13: 5813 | C13: 9423 | D13: =AVERAGE(B13:C13) | E13: Planning £2,813–£3,423 (list + desk calc) + professionals placeholder £3k–£6k
A14: Contingency | B14: 0.1 | E14: Desk estimate
A15: Total build | B15: =SUM(B5:B13)*(1+$B$14) | C15: =SUM(C5:C13)*(1+$B$14) | D15: =SUM(D5:D13)*(1+$B$14)
A17: Paid for by | B17: Low £ | C17: High £ | D17: Middle £ | E17: Source / label
A18: Supplier finance (Zappshelter package) | B18: 87343 | C18: 87343 | D18: =AVERAGE(B18:C18) | E18: Indicative: Zappshelter HP, about £2,000 + VAT a month over 5 years (in the model)
A19: Grants via a CIC | B19: 0 | C19: 0 | D19: =AVERAGE(B19:C19) | E19: None for Arena #1: it runs through the Ltd (Jamie, 29 Oct 2026). A CIC is considered for Arenas #2 and #3
A20: Sponsorship (boards, kit) | B20: 0 | C20: 5000 | D20: =AVERAGE(B20:C20) | E20: Desk estimate: local business sponsors on the arena boards
A21: Still to find (cash or more grants) | B21: =MAX(0,B15-SUM(B18:B20)) | C21: =MAX(0,C15-SUM(C18:C20)) | D21: =MAX(0,D15-SUM(D18:D20)) | E21: Columns pair low build with low funding, high with high

Sheet Funding routes
A1: Funding routes: who applies, for what
A2: Eligibility and amounts are unverified desk research (funder sites could not be checked from this session). Verify before relying on any line.
A4: Route | B4: What it pays for | C4: Who applies | D4: Typical size | E4: Status
A5: Supplier finance (Zappshelter HP or lease) | B5: Canopy, covers, end walls, doors, install | C5: Hoop Heroes Ltd (or CIC) | D5: ~£2,000 + VAT/month over 5 years, or ~£3,000 over 3 | E5: Indicative (29 Oct 2026); terms, VAT and guarantee to confirm
A6: National Lottery Awards for All | B6: Community sessions, kit, small capital | C6: CIC | D6: Up to £20,000 | E6: To verify; not open to profit-making companies
A7: Sport England Movement Fund | B7: Projects getting inactive groups active, incl. kit | C7: CIC | D7: Up to £15,000 (often crowdfund-matched) | E7: To verify
A8: Holiday Activities and Food (Buckinghamshire Council) | B8: Free holiday places for eligible children | C8: Hoop Heroes Ltd as approved provider | D8: Per place per day | E8: To verify rate and provider route
A9: PE and Sport Premium (paid by the school) | B9: PE lesson support and teacher CPD (revenue only) | C9: School buys from Hoop Heroes Ltd | D9: £6,240 + £10 per pupil per school a year | E9: Actual (GOV.UK 2026/27); cannot fund the build
A10: Basketball England and wheelchair basketball funds | B10: Basketball kit, sports wheelchairs, coach courses | C10: CIC or affiliated club | D10: Small grants | E10: To verify
A11: Local council community grants, Section 106 / CIL | B11: Facility capital in the community | C11: CIC | D11: Varies | E11: To verify with Buckinghamshire Council
A12: Local business sponsorship | B12: Arena boards, kit, team shirts | C12: Hoop Heroes Ltd | D12: £500–£5,000 a year | E12: Idea
A14: How the two companies work together (proposal, for the accountant and solicitor)
A15: DECIDED (Jamie, 29 Oct 2026): Arena #1 runs through Hoop Heroes Region 1 Ltd. Once it is open and proven, look at whether a CIC helps fund Arenas #2 and #3. Goal: three Arenas. The proposal below is for that later stage.
A16: Heroes Arena CIC (to be formed): holds the community side. Applies for grants, runs free and community sessions (SEND, wheelchair, girls-only, free sessions), and can hold kit and grant-funded parts of the building.
A17: Hoop Heroes Region 1 Ltd: runs the paid programme (memberships, parties, camps, breakfast, leagues, school PE support) and pays the CIC an arm's-length fee for its use of the space and kit.
A18: The school licenses the site to whichever body holds the Arena; the agreement allows assignment to the CIC later.
A19: Questions to settle first: the CIC asset lock; whether the sports-hire VAT exemption stops the CIC reclaiming VAT on the build; Flat Rate VAT limits for the Ltd; related-party rules and an independent CIC director.
A20: KB position (Project Overview v0.2, decision D1): "Ltd first", forming the CIC when a named grant needs it, is recommended and awaiting Jamie.
